{
    "EnemyAI": {
        "checkpoints": [
            {
                "steps": 999953,
                "file_path": "results\\EnemyAI_Build_Run_16\\EnemyAI\\EnemyAI-999953.onnx",
                "reward": 0.901921167721351,
                "creation_time": 1753803159.0101597,
                "auxillary_file_paths": [
                    "results\\EnemyAI_Build_Run_16\\EnemyAI\\EnemyAI-999953.pt"
                ]
            },
            {
                "steps": 1000081,
                "file_path": "results\\EnemyAI_Build_Run_16\\EnemyAI\\EnemyAI-1000081.onnx",
                "reward": 0.901921167721351,
                "creation_time": 1753803159.071602,
                "auxillary_file_paths": [
                    "results\\EnemyAI_Build_Run_16\\EnemyAI\\EnemyAI-1000081.pt"
                ]
            },
            {
                "steps": 1499947,
                "file_path": "results\\EnemyAI_Build_Run_16\\EnemyAI\\EnemyAI-1499947.onnx",
                "reward": 2.260180023395353,
                "creation_time": 1753812878.0247831,
                "auxillary_file_paths": [
                    "results\\EnemyAI_Build_Run_16\\EnemyAI\\EnemyAI-1499947.pt"
                ]
            },
            {
                "steps": 1999904,
                "file_path": "results\\EnemyAI_Build_Run_16\\EnemyAI\\EnemyAI-1999904.onnx",
                "reward": 2.3644632373936476,
                "creation_time": 1753814703.7279441,
                "auxillary_file_paths": [
                    "results\\EnemyAI_Build_Run_16\\EnemyAI\\EnemyAI-1999904.pt"
                ]
            },
            {
                "steps": 2000032,
                "file_path": "results\\EnemyAI_Build_Run_16\\EnemyAI\\EnemyAI-2000032.onnx",
                "reward": 2.3644632373936476,
                "creation_time": 1753814703.771998,
                "auxillary_file_paths": [
                    "results\\EnemyAI_Build_Run_16\\EnemyAI\\EnemyAI-2000032.pt"
                ]
            }
        ],
        "final_checkpoint": {
            "steps": 2000032,
            "file_path": "results\\EnemyAI_Build_Run_16\\EnemyAI.onnx",
            "reward": 2.3644632373936476,
            "creation_time": 1753814703.771998,
            "auxillary_file_paths": [
                "results\\EnemyAI_Build_Run_16\\EnemyAI\\EnemyAI-2000032.pt"
            ]
        }
    },
    "metadata": {
        "stats_format_version": "0.3.0",
        "mlagents_version": "0.28.0",
        "torch_version": "2.4.1+cu118"
    }
}